AUTHORS
COPYING
ChangeLog
INSTALL
README
conntrack.py
setup.py
packaging/debian-etch/debian/README.Debian
packaging/debian-etch/debian/changelog
packaging/debian-etch/debian/compat
packaging/debian-etch/debian/control
packaging/debian-etch/debian/copyright
packaging/debian-etch/debian/dirs
packaging/debian-etch/debian/docs
packaging/debian-etch/debian/pycompat
packaging/debian-etch/debian/rules
packaging/debian-sarge/debian/README.Debian
packaging/debian-sarge/debian/changelog
packaging/debian-sarge/debian/compat
packaging/debian-sarge/debian/control
packaging/debian-sarge/debian/copyright
packaging/debian-sarge/debian/dirs
packaging/debian-sarge/debian/docs
packaging/debian-sarge/debian/rules
packaging/ubuntu-edgy/debian/README.Debian
packaging/ubuntu-edgy/debian/changelog
packaging/ubuntu-edgy/debian/compat
packaging/ubuntu-edgy/debian/control
packaging/ubuntu-edgy/debian/copyright
packaging/ubuntu-edgy/debian/dirs
packaging/ubuntu-edgy/debian/docs
packaging/ubuntu-edgy/debian/files
packaging/ubuntu-edgy/debian/pycompat
packaging/ubuntu-edgy/debian/rules
pynetfilter_conntrack/__init__.py
pynetfilter_conntrack/conntrack.py
pynetfilter_conntrack/conntrack_entry.py
pynetfilter_conntrack/constant.py
pynetfilter_conntrack/ctypes_errno.py
pynetfilter_conntrack/ctypes_stdint.py
pynetfilter_conntrack/func.py
pynetfilter_conntrack/tools.py
pynetfilter_conntrack/version.py
pynetfilter_conntrack.egg-info/PKG-INFO
pynetfilter_conntrack.egg-info/SOURCES.txt
pynetfilter_conntrack.egg-info/dependency_links.txt
pynetfilter_conntrack.egg-info/requires.txt
pynetfilter_conntrack.egg-info/top_level.txt
pynetfilter_conntrack.egg-info/zip-safe
