Metadata-Version: 1.0
Name: pynetfilter-conntrack
Version: 0.4.2
Summary: pynetfilter_conntrack is a Python binding of libnetfilter_conntrack
Home-page: http://software.inl.fr/trac/trac.cgi/wiki/pynetfilter_conntrack
Author: Victor Stinner
Author-email: victor.stinner AT inl.fr
License: GNU GPL
Download-URL: http://software.inl.fr/trac/trac.cgi/wiki/pynetfilter_conntrack
Keywords: netfilter conntrack ctypes firewall
Platform: Linux
Classifier: Development Status :: 4 - Beta
Classifier: Natural Language :: English
Classifier: Environment :: Console
Classifier: Intended Audience :: Developers
Classifier: Intended Audience :: System Administrators
Classifier: License :: OSI Approved :: GNU General Public License (GPL)
Classifier: Operating System :: POSIX :: Linux
Classifier: Programming Language :: Python
Classifier: Topic :: Software Development :: Libraries :: Python Modules
Classifier: Topic :: System :: Networking :: Firewalls
Classifier: Topic :: System :: Networking :: Monitoring
